Metadata-Version: 2.1
Name: pandas-nql
Version: 1.1.0
Summary: Pandas_nql is an open source Python library that enables natural language queries on Pandas Dataframes using the latest advances in generative AI. Inspired by OpenAI's groundbreaking language models, pandas_nql allows users to analyze data in a more intuitive way - by simply asking questions in plain English instead of writing complex code.
Home-page: https://github.com/jason983/pandas_nql
Author: Jason Beechum
Author-email: jasonbeechum@yahoo.com
License: MIT
Platform: UNKNOWN
Classifier: Intended Audience :: Developers
Classifier: License :: OSI Approved :: MIT License
Classifier: Programming Language :: Python
Classifier: Programming Language :: Python :: 3
Classifier: Programming Language :: Python :: 3.9
Classifier: Programming Language :: Python :: 3.10
Classifier: Programming Language :: Python :: 3.11
Classifier: Operating System :: OS Independent
Requires-Dist: openai
Requires-Dist: duckdb
Requires-Dist: pandas
